shec/__init__.py
shec-0.0.0.dist-info/LICENSE
shec-0.0.0.dist-info/WHEEL
shec-0.0.0.dist-info/METADATA
shec-0.0.0.dist-info/RECORD
