Metadata-Version: 2.1
Name: shec
Version: 0.0.0
Summary: An unofficial Splunk HTTP Endpoint Collector client (and more).
Author: Mark Beacom
Author-email: m@beacom.dev
Requires-Python: >=3.6,<4.0
Classifier: Programming Language :: Python :: 3
Classifier: Programming Language :: Python :: 3.6
Classifier: Programming Language :: Python :: 3.7
Classifier: Programming Language :: Python :: 3.8
Classifier: Programming Language :: Python :: 3.9
Classifier: Programming Language :: Python :: 3.10
Requires-Dist: fire (>=0.4.0,<0.5.0)
Requires-Dist: httpx[brotli,http2] (>=0.19.0,<0.20.0)
Requires-Dist: tenacity (>=8.0.1,<9.0.0)
Requires-Dist: toml (>=0.10.2,<0.11.0)
